flake8_gramex.py
setup.cfg
setup.py
flake8_gramex.egg-info/PKG-INFO
flake8_gramex.egg-info/SOURCES.txt
flake8_gramex.egg-info/dependency_links.txt
flake8_gramex.egg-info/entry_points.txt
flake8_gramex.egg-info/not-zip-safe
flake8_gramex.egg-info/pbr.json
flake8_gramex.egg-info/requires.txt
flake8_gramex.egg-info/top_level.txt