Metadata-Version: 1.1
Name: flake8-gramex
Version: 1.1.1
Summary: Additional validations for Python code
Home-page: https://gramener.com/
Author: Suhas
Author-email: suhas@gramener.com
License: MIT
Keywords: flake8,encoding,unicode
Platform: UNKNOWN
Classifier: Development Status :: 3 - Alpha
Classifier: Environment :: Console
Classifier: Intended Audience :: Developers
Classifier: License :: OSI Approved :: MIT License
Classifier: Operating System :: OS Independent
Classifier: Programming Language :: Python
Classifier: Programming Language :: Python :: 2
Classifier: Programming Language :: Python :: 3
Classifier: Topic :: Software Development :: Libraries :: Python Modules
Classifier: Topic :: Software Development :: Quality Assurance
